{"version":1,"resource":"vscode-remote://ssh-remote%2Bvm-docker/home/leo/backend/routes/solicitudes.js","entries":[{"id":"GbVC.js","timestamp":1770410336166},{"id":"x6cj.js","timestamp":1770413301371},{"id":"Gmnc.js","timestamp":1770414088631},{"id":"dQ7y.js","timestamp":1770414685323},{"id":"Tcuy.js","timestamp":1770415356243},{"id":"FKMW.js","timestamp":1770477086309},{"id":"heAl.js","timestamp":1770477147769},{"id":"BEZY.js","timestamp":1770477802678},{"id":"zePM.js","timestamp":1770478882899},{"id":"taHT.js","timestamp":1770503241705},{"id":"2cXO.js","timestamp":1770503749120},{"id":"bSqb.js","timestamp":1770504097798},{"id":"DTNc.js","timestamp":1770835385675}]}